markdown_doi/__init__.py
markdown_doi/md_doi.py
markdown_doi-1.1.0.dist-info/DESCRIPTION.rst
markdown_doi-1.1.0.dist-info/METADATA
markdown_doi-1.1.0.dist-info/RECORD
markdown_doi-1.1.0.dist-info/WHEEL
markdown_doi-1.1.0.dist-info/metadata.json
markdown_doi-1.1.0.dist-info/top_level.txt
