Metadata-Version: 2.0
Name: markdown-doi
Version: 1.1.0
Summary: Convert doi:10.xxxxx/xxxx to nice bibliographic metadata
Home-page: https://github.com/bcaller/markdown_doi
Author: Ben Caller
Author-email: bcallergmai@l.com
License: AGPLv3
Keywords: doi research journals markdown
Platform: UNKNOWN
Classifier: Development Status :: 4 - Beta
Classifier: Environment :: Console
Classifier: Intended Audience :: Developers
Classifier: Programming Language :: Python
Classifier: Programming Language :: Python :: 2
Classifier: Programming Language :: Python :: 2.7
Classifier: Programming Language :: Python :: 3
Classifier: Programming Language :: Python :: 3.2
Classifier: Programming Language :: Python :: 3.4
Classifier: Programming Language :: Python :: 3.5
Classifier: Programming Language :: Python :: 3.6
Classifier: Topic :: Internet :: WWW/HTTP :: Dynamic Content
Classifier: Topic :: Software Development :: Libraries :: Python Modules
Classifier: Topic :: Text Processing :: Filters
Classifier: Topic :: Text Processing :: Markup :: HTML
Classifier: License :: OSI Approved :: GNU Affero General Public License v3
Requires-Dist: markdown (>=2.5)
Requires-Dist: requests
Provides-Extra: develop
Requires-Dist: pypandoc; extra == 'develop'
